one_puzzle/__init__.py
one_puzzle/__name__.py
one_puzzle/__version__.py
one_puzzle/element.py
one_puzzle/painter.py
one_puzzle/pattern.py
one_puzzle/solver.py
tests/__init__.py
tests/test_element.py
tests/test_painter.py
tests/test_pattern.py
tests/test_solver.py
OnePuzzle-0.2.3.dist-info/LICENSE
OnePuzzle-0.2.3.dist-info/METADATA
OnePuzzle-0.2.3.dist-info/WHEEL
OnePuzzle-0.2.3.dist-info/entry_points.txt
OnePuzzle-0.2.3.dist-info/top_level.txt
OnePuzzle-0.2.3.dist-info/RECORD
