Metadata-Version: 2.1
Name: OnePuzzle
Version: 0.2.3
Summary: Solve puzzle "A Puzzle A Day", get one or all result, show in graphical PyQt5
Home-page: https://github.com/windard/OnePuzzle
Author: Windard Yang
Author-email: windard@qq.com
License: MIT
Keywords: puzzle
Platform: UNKNOWN
Classifier: Programming Language :: Python :: 3.6
Classifier: Programming Language :: Python :: 3.7
Classifier: Programming Language :: Python :: 3.8
Classifier: Programming Language :: Python :: 3.9
Classifier: License :: OSI Approved :: MIT License
Classifier: Operating System :: OS Independent
Requires-Python: >=3.6
License-File: LICENSE
Requires-Dist: PyQt5 (==5.15.4)
Requires-Dist: click (==8.0.1)
Requires-Dist: rich (==10.14.0)
